LICENSE.md
README.md
setup.py
gspa/__init__.py
gspa/embedding.py
gspa/graphs.py
gspa/gspa.py
gspa/version.py
gspa/wavelets.py
gspa.egg-info/PKG-INFO
gspa.egg-info/SOURCES.txt
gspa.egg-info/dependency_links.txt
gspa.egg-info/requires.txt
gspa.egg-info/top_level.txt
tests/test.py