Metadata-Version: 2.2
Name: gspa
Version: 1.1.1
Summary: Gene Signal Pattern Analysis
Home-page: https://github.com/KrishnaswamyLab/Gene-Signal-Pattern-Analysis
Download-URL: https://github.com/KrishnaswamyLab/Gene-Signal-Pattern-Analysis/archive/v1.1.1.tar.gz
Author: Aarthi Venkat, Krishnaswamy Lab, Yale University
Author-email: aarthi.venkat@yale.edu
License: GNU General Public License Version 3
Keywords: big-data,manifold-learning,computational-biology,dimensionality-reduction,single-cell
Classifier: Programming Language :: Python :: 3
Classifier: Programming Language :: Python :: 3.6
Classifier: Programming Language :: Python :: 3.7
Classifier: Programming Language :: Python :: 3.8
Classifier: Programming Language :: Python :: 3.9
Classifier: Topic :: Scientific/Engineering :: Bio-Informatics
Classifier: Intended Audience :: Developers
Classifier: Intended Audience :: Science/Research
Classifier: Natural Language :: English
Classifier: Development Status :: 5 - Production/Stable
Classifier: Operating System :: OS Independent
Requires-Python: >=3.6
License-File: LICENSE.md
Requires-Dist: graphtools>=1.5.0
Requires-Dist: tensorflow>=2.6.0
Requires-Dist: multiscale_phate==0.0
Requires-Dist: numpy>=1.14.0
Requires-Dist: scikit-learn
Requires-Dist: scipy>=1.1.0
Requires-Dist: tqdm
Requires-Dist: scanpy
Requires-Dist: phate
Provides-Extra: test
Requires-Dist: numpy>=1.14.0; extra == "test"
Requires-Dist: phate; extra == "test"
Dynamic: author
Dynamic: author-email
Dynamic: classifier
Dynamic: description
Dynamic: description-content-type
Dynamic: download-url
Dynamic: home-page
Dynamic: keywords
Dynamic: license
Dynamic: provides-extra
Dynamic: requires-dist
Dynamic: requires-python
Dynamic: summary
